arkdriver/__init__.py
arkdriver/main.py
arkdriver/py.typed
arkdriver/driver/__init__.py
arkdriver/driver/application.py
arkdriver/driver/driver.py
arkdriver/driver/run.py
arkdriver/presentation/__init__.py
arkdriver/presentation/presentation.py
arkdriver/session/__init__.py
arkdriver/session/session.py
arkdriver-1.0.16.dist-info/LICENSE
arkdriver-1.0.16.dist-info/METADATA
arkdriver-1.0.16.dist-info/WHEEL
arkdriver-1.0.16.dist-info/top_level.txt
arkdriver-1.0.16.dist-info/RECORD
